skipchunk/__init__.py
skipchunk/cli.py
skipchunk/database.py
skipchunk/elastic.py
skipchunk/enrichquery.py
skipchunk/graphquery.py
skipchunk/html_strip.py
skipchunk/indexquery.py
skipchunk/interfaces.py
skipchunk/payloader.py
skipchunk/skipchunk.py
skipchunk/solr.py
skipchunk/test_output.txt
skipchunk/utilities.py
skipchunk/elastic_home/configsets/skipchunk-graph-configset/__init__.py
skipchunk/elastic_home/configsets/skipchunk-graph-configset/skipchunk-graph-schema.json
skipchunk/elastic_home/configsets/skipchunk-index-configset/__init__.py
skipchunk/elastic_home/configsets/skipchunk-index-configset/skipchunk-index-schema.json
skipchunk/solr_home/.DS_Store
skipchunk/solr_home/__init__.py
skipchunk/solr_home/solr.xml
skipchunk/solr_home/zoo.cfg
skipchunk/solr_home/configsets/.DS_Store
skipchunk/solr_home/configsets/skipchunk-graph-configset/.DS_Store
skipchunk/solr_home/configsets/skipchunk-graph-configset/__init__.py
skipchunk/solr_home/configsets/skipchunk-graph-configset/conf/currency.xml
skipchunk/solr_home/configsets/skipchunk-graph-configset/conf/elevate.xml
skipchunk/solr_home/configsets/skipchunk-graph-configset/conf/managed-schema.old
skipchunk/solr_home/configsets/skipchunk-graph-configset/conf/mapping-FoldToASCII.txt
skipchunk/solr_home/configsets/skipchunk-graph-configset/conf/mapping-ISOLatin1Accent.txt
skipchunk/solr_home/configsets/skipchunk-graph-configset/conf/name_synonyms.txt
skipchunk/solr_home/configsets/skipchunk-graph-configset/conf/protwords.txt
skipchunk/solr_home/configsets/skipchunk-graph-configset/conf/schema.xml
skipchunk/solr_home/configsets/skipchunk-graph-configset/conf/solr-data-config.xml
skipchunk/solr_home/configsets/skipchunk-graph-configset/conf/solrconfig.xml
skipchunk/solr_home/configsets/skipchunk-graph-configset/conf/spellings.txt
skipchunk/solr_home/configsets/skipchunk-graph-configset/conf/stopwords.txt
skipchunk/solr_home/configsets/skipchunk-graph-configset/conf/synonyms.txt
skipchunk-2.0.1.dist-info/AUTHORS.rst
skipchunk-2.0.1.dist-info/LICENSE
skipchunk-2.0.1.dist-info/METADATA
skipchunk-2.0.1.dist-info/WHEEL
skipchunk-2.0.1.dist-info/entry_points.txt
skipchunk-2.0.1.dist-info/top_level.txt
skipchunk-2.0.1.dist-info/RECORD
