Metadata-Version: 2.1
Name: skipchunk
Version: 2.0.1
Summary: Instant Knowledge Graphs from text documents.
Home-page: https://github.com/o19s/skipchunk
Author: Max Irwin
Author-email: mirwin@opensourceconnections.com
License: MIT license
Keywords: skipchunk
Platform: UNKNOWN
Classifier: Development Status :: 4 - Beta
Classifier: Intended Audience :: Developers
Classifier: License :: OSI Approved :: MIT License
Classifier: Natural Language :: English
Classifier: Programming Language :: Python :: 3.8
Requires-Dist: spacy (==3.1.2)
Requires-Dist: nltk (==3.5)
Requires-Dist: pysolr (==3.9.0)
Requires-Dist: elasticsearch (==7.9.1)
Requires-Dist: Click (>=6.0)
Requires-Dist: tqdm (>=4.48)
Requires-Dist: requests (>=2.23)
Requires-Dist: jsonpickle (==1.4.1)
Requires-Dist: bs4 (==0.0.1)
Requires-Dist: lxml (==4.5.2)
Requires-Dist: multidict (==4.7.6)
